sagar/__init__.py
sagar/rexpand.py
sagar/version.py
sagar/crystal/__init__.py
sagar/crystal/derive.py
sagar/crystal/filter.py
sagar/crystal/mutate.py
sagar/crystal/structure.py
sagar/crystal/utils.py
sagar/element/__init__.py
sagar/element/base.py
sagar/io/__init__.py
sagar/io/ase.py
sagar/io/vasp.py
sagar/io/xyz.py
sagar/molecule/__init__.py
sagar/molecule/derive.py
sagar/molecule/structure.py
sagar/molecule/symmetry.py
sagar/toolkit/__init__.py
sagar/toolkit/derivetool.py
sagar/toolkit/mathtool.py
sagar-0.2.1.dist-info/LICENSE
sagar-0.2.1.dist-info/METADATA
sagar-0.2.1.dist-info/WHEEL
sagar-0.2.1.dist-info/entry_points.txt
sagar-0.2.1.dist-info/top_level.txt
sagar-0.2.1.dist-info/RECORD
